extractor/__init__.py
extractor/cli.py
extractor/extract_thumbnails.py
extract_youtube-1.0.0.dist-info/METADATA
extract_youtube-1.0.0.dist-info/WHEEL
extract_youtube-1.0.0.dist-info/entry_points.txt
extract_youtube-1.0.0.dist-info/licenses/LICENSE
extract_youtube-1.0.0.dist-info/RECORD
