Metadata-Version: 2.4
Name: extract-youtube
Version: 1.0.0
Summary: A Python module to extract thumbnail URLs from YouTube video URLs with multiple quality options
Project-URL: Homepage, https://github.com/kevin-celternity/extract-youtube
Project-URL: Bug Reports, https://github.com/kevin-celternity/extract-youtube/issues
Project-URL: Source, https://github.com/kevin-celternity/extract-youtube
Project-URL: Documentation, https://github.com/kevin-celternity/extract-youtube#readme
Author-email: Kevin <kevin@cattt.space>
Maintainer-email: Kevin <kevin@cattt.space>
License: MIT
License-File: LICENSE
Keywords: extractor,image,thumbnail,url,video,youtube
Classifier: Development Status :: 5 - Production/Stable
Classifier: Intended Audience :: Developers
Classifier: License :: OSI Approved :: MIT License
Classifier: Operating System :: OS Independent
Classifier: Programming Language :: Python :: 3
Classifier: Programming Language :: Python :: 3.8
Classifier: Programming Language :: Python :: 3.9
Classifier: Programming Language :: Python :: 3.10
Classifier: Programming Language :: Python :: 3.11
Classifier: Programming Language :: Python :: 3.12
Classifier: Topic :: Internet :: WWW/HTTP
Classifier: Topic :: Multimedia :: Video
Classifier: Topic :: Software Development :: Libraries :: Python Modules
Requires-Python: >=3.8
Requires-Dist: requests>=2.25.0
Provides-Extra: dev
Requires-Dist: black>=21.0; extra == 'dev'
Requires-Dist: flake8>=3.8; extra == 'dev'
Requires-Dist: mypy>=0.900; extra == 'dev'
Requires-Dist: pytest-cov>=2.0; extra == 'dev'
Requires-Dist: pytest>=6.0; extra == 'dev'
